oarepo_documents/__init__.py
oarepo_documents/api.py
oarepo_documents/document_json_mapping.py
oarepo_documents/minter.py
oarepo_documents/version.py
oarepo_documents/included_mappings/v7/document-v1.0.0.json
oarepo_documents/jsonschemas/__init__.py
oarepo_documents/jsonschemas/document-v1.0.0.json
oarepo_documents/marshmallow/__init__.py
oarepo_documents/marshmallow/document.py
oarepo_documents-2.0.1.dist-info/LICENSE
oarepo_documents-2.0.1.dist-info/METADATA
oarepo_documents-2.0.1.dist-info/WHEEL
oarepo_documents-2.0.1.dist-info/entry_points.txt
oarepo_documents-2.0.1.dist-info/top_level.txt
oarepo_documents-2.0.1.dist-info/RECORD
