Metadata-Version: 2.1
Name: oarepo-documents
Version: 2.0.1
Summary: OARepo rdm records data model
Home-page: https://github.com/oarepo/oarepo-dc
Author: Alzbeta Pokorna
Author-email: alzbeta.pokorna@cesnet.cz
License: MIT
Platform: any
Classifier: Environment :: Web Environment
Classifier: Intended Audience :: Developers
Classifier: License :: OSI Approved :: MIT License
Classifier: Operating System :: OS Independent
Classifier: Programming Language :: Python
Classifier: Topic :: Internet :: WWW/HTTP :: Dynamic Content
Classifier: Topic :: Software Development :: Libraries :: Python Modules
Classifier: Programming Language :: Python :: 2
Classifier: Programming Language :: Python :: 2.7
Classifier: Programming Language :: Python :: 3
Classifier: Programming Language :: Python :: 3.5
Classifier: Development Status :: 4 - Beta
Requires-Dist: oarepo-mapping-includes
Requires-Dist: marshmallow
Requires-Dist: flask
Requires-Dist: crossrefapi
Requires-Dist: deepmerge
Requires-Dist: langdetect
Provides-Extra: tests
Requires-Dist: oarepo[tests] (~=3.3.0) ; extra == 'tests'
Requires-Dist: oarepo-records-draft ; extra == 'tests'
Requires-Dist: oarepo-actions ; extra == 'tests'
Requires-Dist: oarepo-validate ; extra == 'tests'
Requires-Dist: coverage ; extra == 'tests'
Requires-Dist: oarepo-multilingual ; extra == 'tests'
Requires-Dist: oarepo-mapping-includes ; extra == 'tests'
Requires-Dist: invenio-search ; extra == 'tests'
Requires-Dist: crossrefapi ; extra == 'tests'
Requires-Dist: deepmerge ; extra == 'tests'
Requires-Dist: langdetect ; extra == 'tests'
Provides-Extra: tests-es7
Requires-Dist: oarepo[tests-es7] (~=3.3.0) ; extra == 'tests-es7'
Requires-Dist: oarepo-records-draft ; extra == 'tests-es7'
Requires-Dist: oarepo-actions ; extra == 'tests-es7'
Requires-Dist: oarepo-validate ; extra == 'tests-es7'
Requires-Dist: coverage ; extra == 'tests-es7'
Requires-Dist: oarepo-multilingual ; extra == 'tests-es7'
Requires-Dist: oarepo-mapping-includes ; extra == 'tests-es7'
Requires-Dist: invenio-search ; extra == 'tests-es7'
Requires-Dist: crossrefapi ; extra == 'tests-es7'
Requires-Dist: deepmerge ; extra == 'tests-es7'
Requires-Dist: langdetect ; extra == 'tests-es7'
